Metadata-Version: 1.0
Name: FBot
Version: 0.0.1
Summary: FBot - A python liabrary, In which you can generate chat bots effortlessly.
Home-page: https://github.com/back-2-hack
Author: B2H
Author-email: back2hacck@gmail.com
License: UNKNOWN
Keywords: chat_bot
Platform: UNKNOWN
